skill_framework/__init__.py
skill_framework/common.py
skill_framework/diagnostics.py
skill_framework/layouts.py
skill_framework/package.py
skill_framework/pipelines.py
skill_framework/preview.py
skill_framework/resources.py
skill_framework/skills.py
skill_framework/testing.py
skill_framework/util.py
skill_framework/server/__init__.py
skill_framework/server/main.py
skill_framework/server/ui/asset-manifest.json
skill_framework/server/ui/index.html
skill_framework/server/ui/manifest.json
skill_framework/server/ui/robots.txt
skill_framework/server/ui/static/max-favicon-filled.png
skill_framework/server/ui/static/css/main.3dbe0a45.css
skill_framework/server/ui/static/css/main.3dbe0a45.css.map
skill_framework/server/ui/static/js/10291.fd1dfd93.chunk.js
skill_framework/server/ui/static/js/10370.282c4ab9.chunk.js
skill_framework/server/ui/static/js/10375.14e00fbf.chunk.js
skill_framework/server/ui/static/js/10448.98b2baa0.chunk.js
skill_framework/server/ui/static/js/1070.75f01f2d.chunk.js
skill_framework/server/ui/static/js/10833.4d913468.chunk.js
skill_framework/server/ui/static/js/10927.fad3b278.chunk.js
skill_framework/server/ui/static/js/11139.fdeb4ac2.chunk.js
skill_framework/server/ui/static/js/11153.1828c185.chunk.js
skill_framework/server/ui/static/js/1116.2067a7e0.chunk.js
skill_framework/server/ui/static/js/11437.5aecf77f.chunk.js
skill_framework/server/ui/static/js/11463.126d3a0f.chunk.js
skill_framework/server/ui/static/js/1162.64e94fc0.chunk.js
skill_framework/server/ui/static/js/12723.f04683d3.chunk.js
skill_framework/server/ui/static/js/12772.05161fb2.chunk.js
skill_framework/server/ui/static/js/12876.185d6396.chunk.js
skill_framework/server/ui/static/js/129.8f46e431.chunk.js
skill_framework/server/ui/static/js/13102.b3f88b3a.chunk.js
skill_framework/server/ui/static/js/13173.a8541a89.chunk.js
skill_framework/server/ui/static/js/13209.60df0b63.chunk.js
skill_framework/server/ui/static/js/1361.ee9d0d01.chunk.js
skill_framework-0.3.18.dist-info/METADATA
skill_framework-0.3.18.dist-info/WHEEL
skill_framework-0.3.18.dist-info/entry_points.txt
skill_framework-0.3.18.dist-info/top_level.txt
skill_framework-0.3.18.dist-info/RECORD
