Metadata-Version: 2.4
Name: skill-framework
Version: 0.3.18
Summary: AnswerRocket skill framework
Requires-Python: >=3.10.7
Requires-Dist: pydantic
Requires-Dist: pathspec
Requires-Dist: jinja2
Requires-Dist: dotenv
Provides-Extra: ui
Requires-Dist: fastapi[standard]; extra == "ui"
Provides-Extra: test
Requires-Dist: pytest; extra == "test"
